hion/__init__.py
hion/controller.py
hion/distribution.py
hion/dynamics.py
hion/types.py
hionx-0.1.0.dist-info/METADATA
hionx-0.1.0.dist-info/WHEEL
hionx-0.1.0.dist-info/top_level.txt
hionx-0.1.0.dist-info/RECORD
