Metadata-Version: 2.2
Name: hionx
Version: 0.1.0
Summary: Hion (/ˈiː.ɒn/): Hamiltonian-Informed Optimal Neural Control
Author-email: Josue N Rivera <josue.n.rivera@outlook.com>
Project-URL: Homepage, https://github.com/wzjoriv/Hion
Project-URL: Issues, https://github.com/wzjoriv/Hion/issues
Classifier: Programming Language :: Python :: 3
Classifier: Operating System :: OS Independent
Requires-Python: >=3.13
Requires-Dist: torch
Requires-Dist: numpy
